{
  "title": "LG’s monitors come with an unwanted addition for Windows: McAfee pop-up ads",
  "summary": "The LG Monitor App Installer installs itself by default and has started pushing unwanted ad notifications to users’ screens. The LG Monitor App Installer installs itself by default and has started pushing unwanted ad notifications to users’ screens.",
  "source": "The Verge",
  "url": "https://theverge.com/tech/967983/lg-monitors-mcafee-adware-gamers-nexus",
  "published_utc": "2026-07-20T16:14:58+00:00",
  "date_source": "meta",
  "generated_utc": "2026-07-20T17:54:02.938665+00:00",
  "maximum_news_age_hours": 72,
  "hero_image_url": "https://platform.theverge.com/wp-content/uploads/sites/2/2026/07/lg-ultragear-34-inch-monitor.jpeg?quality=90&strip=all&crop=0%2C3.4613147178592%2C100%2C93.077370564282&w=1200",
  "hero_image_used": true,
  "fallback_image_used": false,
  "current_run_download_only": true,
  "image_candidates_checked": 12,
  "theme_accent_rgb": [
    226,
    42,
    166
  ],
  "image": "output/2026-07-20/lg-s-monitors-come-with-an-unwanted-addition-for-windows-mcafee-pop-up.png",
  "caption": "output/2026-07-20/lg-s-monitors-come-with-an-unwanted-addition-for-windows-mcafee-pop-up.txt"
}