{
  "title": "StrictlyVC returns to New York City September 10 to celebrate a huge year for the city’s startup community",
  "summary": "Overall, New York startups raised a whopping $16 billion in the first half this year — nearly matching the $19.1 billion that New York startups raised across all of 2025.",
  "source": "TechCrunch",
  "url": "https://techcrunch.com/2026/07/20/strictlyvc-returns-to-new-york-city-september-10-to-celebrate-a-huge-year-for-the-citys-startup-community",
  "published_utc": "2026-07-20T12:30:00+00:00",
  "date_source": "rss",
  "generated_utc": "2026-07-20T13:17:45.532228+00:00",
  "maximum_news_age_hours": 72,
  "hero_image_url": "https://techcrunch.com/wp-content/uploads/2025/04/StrictlyVC-NYC-2024.jpg?resize=1200,800",
  "hero_image_used": true,
  "fallback_image_used": false,
  "current_run_download_only": true,
  "image_candidates_checked": 2,
  "theme_accent_rgb": [
    16,
    185,
    110
  ],
  "image": "output/2026-07-20/strictlyvc-returns-to-new-york-city-september-10-to-celebrate-a-huge-y.png",
  "caption": "output/2026-07-20/strictlyvc-returns-to-new-york-city-september-10-to-celebrate-a-huge-y.txt"
}