{
  "title": "2026 Leagues Cup Livestream: How to Watch Every Match (Even for Free)",
  "summary": "This includes the defending Leagues Cup champion Seattle Sounders, the 2025 MLS Cup Champion Inter Miami, top Liga MX champion Club Toluca, as well as 2025 Concacaf Champions Cup winner Cruz Azul and runner-up Vancouver Whitecaps.",
  "source": "PCMag News",
  "url": "https://pcmag.com/news/how-to-watch-the-2026-leagues-cup-live-without-cable-even-for-free",
  "published_utc": "2026-07-22T12:15:00+00:00",
  "date_source": "meta",
  "generated_utc": "2026-07-22T14:22:21.419846+00:00",
  "maximum_news_age_hours": 72,
  "hero_image_url": "https://i.pcmag.com/imagery/articles/03NHKGA9CF09okyfH9e1K4e-5.fit_lim.size_1200x630.v1784666702.jpg",
  "hero_image_used": true,
  "fallback_image_used": false,
  "current_run_download_only": true,
  "image_candidates_checked": 6,
  "theme_accent_rgb": [
    84,
    153,
    255
  ],
  "image": "output/2026-07-22/2026-leagues-cup-livestream-how-to-watch-every-match-even-for-free.png",
  "caption": "output/2026-07-22/2026-leagues-cup-livestream-how-to-watch-every-match-even-for-free.txt"
}