{
  "title": "Google is making it easier to switch from iPhone to Android | TechCrunch",
  "summary": "With this new method, users can transfer photos, videos, contacts, messages, calendars, and newly supported data types, including their Google Account, passwords, Wi-Fi credentials, and even their eSIM, when switching from an iPhone to Android.",
  "source": "TechCrunch",
  "url": "https://techcrunch.com/2026/07/22/google-is-making-it-easier-to-switch-from-iphone-to-android",
  "published_utc": "2026-07-22T17:08:03+00:00",
  "date_source": "meta",
  "generated_utc": "2026-07-22T18:13:16.119168+00:00",
  "maximum_news_age_hours": 72,
  "hero_image_url": "https://techcrunch.com/wp-content/uploads/2026/07/Screenshot-2026-07-22-at-12.32.37-PM.png?resize=1200,669",
  "hero_image_used": true,
  "fallback_image_used": false,
  "current_run_download_only": true,
  "image_candidates_checked": 4,
  "theme_accent_rgb": [
    16,
    185,
    110
  ],
  "image": "output/2026-07-22/google-is-making-it-easier-to-switch-from-iphone-to-android-techcrunch.png",
  "caption": "output/2026-07-22/google-is-making-it-easier-to-switch-from-iphone-to-android-techcrunch.txt"
}