{
  "title": "Origin Energy investigates potential breach of customer data",
  "summary": "Origin Energy, Australia’s largest electricity and gas retailer, told the Australian Securities Exchange on 22 July that it is investigating potential unauthorised access to some of its customers’ data. The company has promised a further update once its investigation firms up.",
  "source": "The Next Web",
  "url": "https://thenextweb.com/news/origin-energy-investigates-potential-breach-of-customer-data",
  "published_utc": "2026-07-22T08:53:19+00:00",
  "date_source": "meta",
  "generated_utc": "2026-07-22T09:38:45.921956+00:00",
  "maximum_news_age_hours": 72,
  "hero_image_url": "https://media.thenextweb.com/2026/07/Origin-Energy.avif",
  "hero_image_used": true,
  "fallback_image_used": false,
  "current_run_download_only": true,
  "image_candidates_checked": 6,
  "theme_accent_rgb": [
    84,
    153,
    255
  ],
  "image": "output/2026-07-22/origin-energy-investigates-potential-breach-of-customer-data.png",
  "caption": "output/2026-07-22/origin-energy-investigates-potential-breach-of-customer-data.txt"
}