{
  "title": "I’m a Deals Writer, and These Are My Top 10 Tech Deals This Week",
  "summary": "If you’ve never owned a Garmin watch and want to try one out, now is a good time : The best budget Garmin for runners, the Garmin Forerunner 55 , is down to its lowest price ever—$129 (originally $199.99).",
  "source": "Lifehacker",
  "url": "https://lifehacker.com/tech/best-tech-deals-this-week",
  "published_utc": "2026-07-17T19:30:00+00:00",
  "date_source": "meta",
  "generated_utc": "2026-07-20T08:16:13.876326+00:00",
  "maximum_news_age_hours": 72,
  "hero_image_url": "https://lifehacker.com/imagery/articles/01JVZABKMFK8VHA1KJ8C41P3B1/hero-image.png",
  "hero_image_used": true,
  "fallback_image_used": false,
  "current_run_download_only": true,
  "image_candidates_checked": 12,
  "theme_accent_rgb": [
    84,
    153,
    255
  ],
  "image": "output/2026-07-17/i-m-a-deals-writer-and-these-are-my-top-10-tech-deals-this-week.png",
  "caption": "output/2026-07-17/i-m-a-deals-writer-and-these-are-my-top-10-tech-deals-this-week.txt"
}