{
  "title": "Europe hits Google with $1 billion fine for boxing-out rivals - Engadget",
  "summary": "The move is bound to raise the Trump administration's ire against the bloc. Europe has hit Google with €890 million ($1 billion) fine for illegally abusing its search engine \"gatekeeper\" dominance against competition, the EU Commission said in a press release .",
  "source": "Engadget",
  "url": "https://engadget.com/2221542/eu-google-fine-1-billion-dma",
  "published_utc": "2026-07-23T11:17:59+00:00",
  "date_source": "meta",
  "generated_utc": "2026-07-23T12:02:46.447254+00:00",
  "maximum_news_age_hours": 72,
  "hero_image_url": "https://www.engadget.com/img/gallery/europe-hits-google-with-1-billion-fine-for-boxing-out-rivals/l-intro-1784805369.jpg",
  "hero_image_used": true,
  "fallback_image_used": false,
  "current_run_download_only": true,
  "image_candidates_checked": 2,
  "theme_accent_rgb": [
    84,
    153,
    255
  ],
  "image": "output/2026-07-23/europe-hits-google-with-1-billion-fine-for-boxing-out-rivals-engadget.png",
  "caption": "output/2026-07-23/europe-hits-google-with-1-billion-fine-for-boxing-out-rivals-engadget.txt"
}