{
  "title": "Google adds selfie video as a log-in option - Engadget",
  "summary": "It’s another way to use your face for identity verification. You'll now be able to use selfie videos to log into your Google account.",
  "source": "Engadget",
  "url": "https://engadget.com/2221520/google-adds-selfie-video-log-in",
  "published_utc": "2026-07-23T10:00:00+00:00",
  "date_source": "meta",
  "generated_utc": "2026-07-23T10:03:39.190405+00:00",
  "maximum_news_age_hours": 72,
  "hero_image_url": "https://www.engadget.com/img/gallery/google-adds-selfie-video-as-a-log-in-option/l-intro-1784799756.jpg",
  "hero_image_used": true,
  "fallback_image_used": false,
  "current_run_download_only": true,
  "image_candidates_checked": 3,
  "theme_accent_rgb": [
    84,
    153,
    255
  ],
  "image": "output/2026-07-23/google-adds-selfie-video-as-a-log-in-option-engadget.png",
  "caption": "output/2026-07-23/google-adds-selfie-video-as-a-log-in-option-engadget.txt"
}