{
  "title": "China weighs export controls on its own AI models and chips, FT reports",
  "summary": "China is considering tightening export controls on its home-grown artificial intelligence models and the chips that run them, according to the Financial Times, in a move that would push Beijing’s technology defences well beyond the raw materials and equipment it already guards.",
  "source": "The Next Web",
  "url": "https://thenextweb.com/news/china-ai-model-chip-export-controls-ft-report",
  "published_utc": "2026-07-21T08:29:55+00:00",
  "date_source": "meta",
  "generated_utc": "2026-07-21T08:43:20.559504+00:00",
  "maximum_news_age_hours": 72,
  "hero_image_url": "https://media.thenextweb.com/2026/06/china-ai-global-cooperation-vs-g7-export-controls.avif",
  "hero_image_used": true,
  "fallback_image_used": false,
  "current_run_download_only": true,
  "image_candidates_checked": 6,
  "theme_accent_rgb": [
    84,
    153,
    255
  ],
  "image": "output/2026-07-21/china-weighs-export-controls-on-its-own-ai-models-and-chips-ft-reports.png",
  "caption": "output/2026-07-21/china-weighs-export-controls-on-its-own-ai-models-and-chips-ft-reports.txt"
}