{
  "title": "The best budget OLED TV you can buy just had its price slashed to under $600 at Best Buy",
  "summary": "News, deals, reviews, guides and more on the newest computing gadgets Start exploring exclusive deals, expert advice and more Sign up for breaking news, reviews, opinion, top tech deals, and more.",
  "source": "TechRadar",
  "url": "https://techradar.com/televisions/the-best-budget-oled-tv-you-can-buy-just-had-its-price-slashed-to-under-usd600-at-best-buy",
  "published_utc": "2026-07-21T14:16:27+00:00",
  "date_source": "rss",
  "generated_utc": "2026-07-21T14:20:02.120797+00:00",
  "maximum_news_age_hours": 72,
  "hero_image_url": "https://cdn.mos.cms.futurecdn.net/TLVL2aZtS6wxSWcozfnspb-1280-80.jpg",
  "hero_image_used": true,
  "fallback_image_used": false,
  "current_run_download_only": true,
  "image_candidates_checked": 12,
  "theme_accent_rgb": [
    84,
    153,
    255
  ],
  "image": "output/2026-07-21/the-best-budget-oled-tv-you-can-buy-just-had-its-price-slashed-to-unde.png",
  "caption": "output/2026-07-21/the-best-budget-oled-tv-you-can-buy-just-had-its-price-slashed-to-unde.txt"
}