{
  "title": "These 4 DIY Builds Blow Away Valve's Steam Machine, and One Saves You $150",
  "summary": "Valve's exciting new Steam Machine gaming desktop has landed, but it's not the affordable dream machine many PC gamers expected. The Steam Machine’s default operating system is Valve’s SteamOS.",
  "source": "PCMag News",
  "url": "https://pcmag.com/news/these-4-diy-builds-blow-away-valves-steam-machine-and-one-saves-you-150",
  "published_utc": "2026-07-21T13:54:02+00:00",
  "date_source": "meta",
  "generated_utc": "2026-07-21T14:20:25.692907+00:00",
  "maximum_news_age_hours": 72,
  "hero_image_url": "",
  "hero_image_used": false,
  "fallback_image_used": true,
  "current_run_download_only": true,
  "image_candidates_checked": 5,
  "theme_accent_rgb": [
    84,
    153,
    255
  ],
  "image": "output/2026-07-21/these-4-diy-builds-blow-away-valve-s-steam-machine-and-one-saves-you-1.png",
  "caption": "output/2026-07-21/these-4-diy-builds-blow-away-valve-s-steam-machine-and-one-saves-you-1.txt"
}